simplebot_chain_reaction/__init__.py
simplebot_chain_reaction/game.py
simplebot_chain_reaction/orm.py
simplebot_chain_reaction-1.0.0.dist-info/LICENSE
simplebot_chain_reaction-1.0.0.dist-info/METADATA
simplebot_chain_reaction-1.0.0.dist-info/WHEEL
simplebot_chain_reaction-1.0.0.dist-info/entry_points.txt
simplebot_chain_reaction-1.0.0.dist-info/top_level.txt
simplebot_chain_reaction-1.0.0.dist-info/RECORD
